aicli/__init__.py
aicli/agentlib.py
aicli/cli.py
aicli/conf.py
aicli/decorator.py
aicli/role.py
aicli/tools.py
aicli_agent-0.1.4.dist-info/METADATA
aicli_agent-0.1.4.dist-info/WHEEL
aicli_agent-0.1.4.dist-info/entry_points.txt
aicli_agent-0.1.4.dist-info/top_level.txt
aicli_agent-0.1.4.dist-info/RECORD
