Metadata-Version: 2.4
Name: aicli-agent
Version: 0.1.4
Home-page: https://github.com/callmexss/aicli
Project-URL: PyPI, https://pypi.org/project/aicli-agent/
Requires-Dist: Click
Requires-Dist: pydantic-settings
Requires-Dist: generalagent
Requires-Dist: rich
Requires-Dist: tavily-python
Dynamic: description
Dynamic: description-content-type
Dynamic: home-page
Dynamic: project-url
Dynamic: requires-dist
